starsalign/__init__.py
starsalign-1.1.0.dist-info/LICENSE
starsalign-1.1.0.dist-info/METADATA
starsalign-1.1.0.dist-info/WHEEL
starsalign-1.1.0.dist-info/top_level.txt
starsalign-1.1.0.dist-info/RECORD
