Metadata-Version: 2.1
Name: starsalign
Version: 1.1.0
Summary: A package for aligning and comparing astronomical images
Home-page: https://github.com/nagonzalezf/starsalign
Author: Nicolas Antonio Gonzalez Figueroa
Author-email: nagonzalezf@ing.ucsc.cl
Project-URL: Source Code, https://github.com/nagonzalezf/starsalign/starsalign
Project-URL: Bug Tracker, https://github.com/nagonzalezf/starsalign/issues
Keywords: align alignment alignment-algorithm astro astronomy astronomical-images astrophysics         displacement-estimation difference-image-analysis flann-matchers galaxies image-processing         image-subtraction keypoint-detection numpy opencv sift-algorithm stars starsalign
Classifier: Intended Audience :: Developers
Classifier: Intended Audience :: Science/Research
Classifier: License :: OSI Approved :: MIT License
Classifier: Natural Language :: English
Classifier: Programming Language :: Python
Classifier: Programming Language :: Python :: 3
Classifier: Programming Language :: Python :: 3.10
Classifier: Programming Language :: Python :: 3.11
Classifier: Programming Language :: Python :: 3.12
Classifier: Topic :: Scientific/Engineering
Classifier: Topic :: Scientific/Engineering :: Astronomy
Classifier: Topic :: Scientific/Engineering :: Image Processing
License-File: LICENSE
Requires-Dist: numpy
Requires-Dist: opencv-python-headless
